main.py
setup.py
midi_melady_extraction.egg-info/PKG-INFO
midi_melady_extraction.egg-info/SOURCES.txt
midi_melady_extraction.egg-info/dependency_links.txt
midi_melady_extraction.egg-info/requires.txt
midi_melady_extraction.egg-info/top_level.txt